README.md
setup.cfg
setup.py
cloudmersive_nlp_api_client/__init__.py
cloudmersive_nlp_api_client/api_client.py
cloudmersive_nlp_api_client/configuration.py
cloudmersive_nlp_api_client/rest.py
cloudmersive_nlp_api_client.egg-info/PKG-INFO
cloudmersive_nlp_api_client.egg-info/SOURCES.txt
cloudmersive_nlp_api_client.egg-info/dependency_links.txt
cloudmersive_nlp_api_client.egg-info/requires.txt
cloudmersive_nlp_api_client.egg-info/top_level.txt
cloudmersive_nlp_api_client/api/__init__.py
cloudmersive_nlp_api_client/api/analytics_api.py
cloudmersive_nlp_api_client/api/extract_entities_api.py
cloudmersive_nlp_api_client/api/language_detection_api.py
cloudmersive_nlp_api_client/api/language_translation_api.py
cloudmersive_nlp_api_client/api/parse_api.py
cloudmersive_nlp_api_client/api/pos_tagger_api.py
cloudmersive_nlp_api_client/api/rephrase_api.py
cloudmersive_nlp_api_client/api/segmentation_api.py
cloudmersive_nlp_api_client/api/spellcheck_api.py
cloudmersive_nlp_api_client/models/__init__.py
cloudmersive_nlp_api_client/models/check_sentence_request.py
cloudmersive_nlp_api_client/models/check_sentence_response.py
cloudmersive_nlp_api_client/models/check_word_request.py
cloudmersive_nlp_api_client/models/check_word_response.py
cloudmersive_nlp_api_client/models/correct_word_in_sentence.py
cloudmersive_nlp_api_client/models/entity.py
cloudmersive_nlp_api_client/models/extract_entities_request.py
cloudmersive_nlp_api_client/models/extract_entities_response.py
cloudmersive_nlp_api_client/models/get_words_request.py
cloudmersive_nlp_api_client/models/get_words_response.py
cloudmersive_nlp_api_client/models/hate_speech_analysis_request.py
cloudmersive_nlp_api_client/models/hate_speech_analysis_response.py
cloudmersive_nlp_api_client/models/language_detection_request.py
cloudmersive_nlp_api_client/models/language_detection_response.py
cloudmersive_nlp_api_client/models/language_translation_request.py
cloudmersive_nlp_api_client/models/language_translation_response.py
cloudmersive_nlp_api_client/models/parse_request.py
cloudmersive_nlp_api_client/models/parse_response.py
cloudmersive_nlp_api_client/models/pos_request.py
cloudmersive_nlp_api_client/models/pos_response.py
cloudmersive_nlp_api_client/models/pos_sentence.py
