Metadata-Version: 2.1
Name: cloudmersive-nlp-api-client
Version: 4.0.1
Summary: nlpapiv2
Home-page: https://www.cloudmersive.com/nlp-api
Author-email: 
License: UNKNOWN
Keywords: Swagger,nlpapiv2
Platform: UNKNOWN
